sanic_uzi/__init__.py
sanic_uzi/ext/__init__.py
sanic_uzi/ext/extension.py
sanic_uzi-0.0.0.dist-info/LICENSE.txt
sanic_uzi-0.0.0.dist-info/WHEEL
sanic_uzi-0.0.0.dist-info/METADATA
sanic_uzi-0.0.0.dist-info/RECORD
