Metadata-Version: 2.1
Name: sanic-uzi
Version: 0.0.0
Summary: Sanic uzi adapter
Home-page: https://github.com/pyuzi/sanic-uzi
License: MIT
Keywords: dependency-injection,inversion-of-control,sanic-dependency-injection,inversion-of-control-container,IoC-Container,service-injector,injector,sanic-uzi,IoC,DI,Uzi
Author: David Kyalo
Author-email: davidmkyalo@gmail.com
Requires-Python: >=3.9,<4.0
Classifier: License :: OSI Approved :: MIT License
Classifier: Programming Language :: Python :: 3
Classifier: Programming Language :: Python :: 3.10
Classifier: Programming Language :: Python :: 3.9
Requires-Dist: sanic[ext] (>=22.3.1,<23.0.0)
Requires-Dist: typing-extensions (>=4.1.1,<5.0.0)
Requires-Dist: uzi (>=0.0.0,<0.1.0)
Project-URL: Documentation, https://pyuzi.github.io/uzi
Project-URL: Repository, https://github.com/pyuzi/sanic-uzi
